{
  "name": "one-way-caravan-nightfall",
  "tree": {
    "$className": "DataModel",
    "ServerScriptService": {
      "$className": "ServerScriptService",
      "OneWayCaravanNightfallServer": {
        "$path": "src/ServerScriptService/OneWayCaravanNightfallServer.server.lua"
      }
    },
    "StarterPlayer": {
      "$className": "StarterPlayer",
      "StarterPlayerScripts": {
        "$className": "StarterPlayerScripts",
        "OneWayCaravanNightfallClient": {
          "$path": "src/StarterPlayer/StarterPlayerScripts/OneWayCaravanNightfallClient.client.lua"
        }
      }
    }
  }
}
